{
  "category": "סדנאות בריאות",
  "description": "סדנאות בריאות הן חלק חשוב מתוכניות קידום הבריאות של קופות החולים. הן מציעות מגוון רחב של פעילויות חינוכיות ומעשיות המיועדות לשפר את בריאות המבוטחים, להקנות ידע ומיומנויות לאורח חיים בריא, ולסייע בהתמודדות עם מצבי בריאות שונים. הטבלה שלהלן מציגה את הסדנאות העיקריות המוצעות על ידי קופות החולים \"מכבי\", \"מאוחדת\" ו\"כללית\" ואת ההטבות הניתנות למבוטחים במסלולי הביטוח השונים. הסדנאות המוצגות כוללות:",
  "hmo": "מאוחדת",
  "tier": "ארד",
  "services": [
    {
      "name": "הפסקת עישון",
      "benefits": "30% הנחה"
    },
    {
      "name": "תזונה נכונה",
      "benefits": "35% הנחה"
    },
    {
      "name": "פעילות גופנית",
      "benefits": "25% הנחה"
    },
    {
      "name": "ניהול מתח",
      "benefits": "40% הנחה"
    },
    {
      "name": "סוכרת",
      "benefits": "45% הנחה"
    },
    {
      "name": "הריון ולידה",
      "benefits": "35% הנחה"
    }
  ],
  "contact": {
    "מספרי_טלפון_להרשמה_לסדנאות:": "3833* או 1-222-3833 שלוחה 8",
    "phone": "1-222-3833",
    "website": "https://www.meuhedet.co.il/health-workshops"
  }
}